supercalculadora/__init__.py
supercalculadora-1.0.0.dist-info/METADATA
supercalculadora-1.0.0.dist-info/WHEEL
supercalculadora-1.0.0.dist-info/entry_points.txt
supercalculadora-1.0.0.dist-info/top_level.txt
supercalculadora-1.0.0.dist-info/RECORD
